__init__.py
onepager.py
onepager-0.1.dist-info/LICENSE.txt
onepager-0.1.dist-info/METADATA
onepager-0.1.dist-info/WHEEL
onepager-0.1.dist-info/entry_points.txt
onepager-0.1.dist-info/top_level.txt
onepager-0.1.dist-info/RECORD
