Metadata-Version: 2.1
Name: onepager
Version: 0.1
Summary: OnePager allows you to create simple and easy-to-navigate documentation for all your projects
Author: Julien Blanchard
Requires-Python: >=3.7
License-File: LICENSE.txt
Requires-Dist: datetime
Requires-Dist: typing
Requires-Dist: mistune
